<?xml version="1.0" encoding="UTF-8"?>
<SOAP-ENV:Envelope
 xmlns:SOAP-ENV="http://schemas.xmlsoap.org/soap/envelope/"
 xmlns:SOAP-ENC="http://schemas.xmlsoap.org/soap/encoding/"
 xmlns:xsi="http://www.w3.org/2001/XMLSchema-instance"
 xmlns:xsd="http://www.w3.org/2001/XMLSchema"
 xmlns:ns1="http://tempuri.org/">
 <SOAP-ENV:Body>
  <ns1:GetDevicesResponse>
   <ns1:GetDevicesResult>
    <ns1:SoapDeviceDescriptor>
     <ns1:DeviceConnectionPoints>
      <ns1:SoapConnectionPointDescriptor>
       <ns1:Properties>
        <ns1:SoapPropertyDescriptor>
         <ns1:Name></ns1:Name>
         <ns1:DataType></ns1:DataType>
         <ns1:Value></ns1:Value>
        </ns1:SoapPropertyDescriptor>
        <ns1:SoapPropertyDescriptor>
         <ns1:Name></ns1:Name>
         <ns1:DataType></ns1:DataType>
         <ns1:Value></ns1:Value>
        </ns1:SoapPropertyDescriptor>
       </ns1:Properties>
      </ns1:SoapConnectionPointDescriptor>
      <ns1:SoapConnectionPointDescriptor>
       <ns1:Properties>
        <ns1:SoapPropertyDescriptor>
         <ns1:Name></ns1:Name>
         <ns1:DataType></ns1:DataType>
         <ns1:Value></ns1:Value>
        </ns1:SoapPropertyDescriptor>
        <ns1:SoapPropertyDescriptor>
         <ns1:Name></ns1:Name>
         <ns1:DataType></ns1:DataType>
         <ns1:Value></ns1:Value>
        </ns1:SoapPropertyDescriptor>
       </ns1:Properties>
      </ns1:SoapConnectionPointDescriptor>
     </ns1:DeviceConnectionPoints>
     <ns1:Pinouts>
      <ns1:SoapPinoutDescriptor>
       <ns1:SupportedCommands>
        <ns1:SoapCommandDescriptor>
         <ns1:CommandParameters>
         </ns1:CommandParameters>
         <ns1:Properties>
         </ns1:Properties>
        </ns1:SoapCommandDescriptor>
        <ns1:SoapCommandDescriptor>
         <ns1:CommandParameters>
         </ns1:CommandParameters>
         <ns1:Properties>
         </ns1:Properties>
        </ns1:SoapCommandDescriptor>
       </ns1:SupportedCommands>
       <ns1:SupportedEvents>
        <ns1:SoapEventDescriptor>
         <ns1:EventParameters>
         </ns1:EventParameters>
         <ns1:Properties>
         </ns1:Properties>
        </ns1:SoapEventDescriptor>
        <ns1:SoapEventDescriptor>
         <ns1:EventParameters>
         </ns1:EventParameters>
         <ns1:Properties>
         </ns1:Properties>
        </ns1:SoapEventDescriptor>
       </ns1:SupportedEvents>
       <ns1:Properties>
        <ns1:SoapPropertyDescriptor>
         <ns1:Name></ns1:Name>
         <ns1:DataType></ns1:DataType>
         <ns1:Value></ns1:Value>
        </ns1:SoapPropertyDescriptor>
        <ns1:SoapPropertyDescriptor>
         <ns1:Name></ns1:Name>
         <ns1:DataType></ns1:DataType>
         <ns1:Value></ns1:Value>
        </ns1:SoapPropertyDescriptor>
       </ns1:Properties>
      </ns1:SoapPinoutDescriptor>
      <ns1:SoapPinoutDescriptor>
       <ns1:SupportedCommands>
        <ns1:SoapCommandDescriptor>
         <ns1:CommandParameters>
         </ns1:CommandParameters>
         <ns1:Properties>
         </ns1:Properties>
        </ns1:SoapCommandDescriptor>
        <ns1:SoapCommandDescriptor>
         <ns1:CommandParameters>
         </ns1:CommandParameters>
         <ns1:Properties>
         </ns1:Properties>
        </ns1:SoapCommandDescriptor>
       </ns1:SupportedCommands>
       <ns1:SupportedEvents>
        <ns1:SoapEventDescriptor>
         <ns1:EventParameters>
         </ns1:EventParameters>
         <ns1:Properties>
         </ns1:Properties>
        </ns1:SoapEventDescriptor>
        <ns1:SoapEventDescriptor>
         <ns1:EventParameters>
         </ns1:EventParameters>
         <ns1:Properties>
         </ns1:Properties>
        </ns1:SoapEventDescriptor>
       </ns1:SupportedEvents>
       <ns1:Properties>
        <ns1:SoapPropertyDescriptor>
         <ns1:Name></ns1:Name>
         <ns1:DataType></ns1:DataType>
         <ns1:Value></ns1:Value>
        </ns1:SoapPropertyDescriptor>
        <ns1:SoapPropertyDescriptor>
         <ns1:Name></ns1:Name>
         <ns1:DataType></ns1:DataType>
         <ns1:Value></ns1:Value>
        </ns1:SoapPropertyDescriptor>
       </ns1:Properties>
      </ns1:SoapPinoutDescriptor>
     </ns1:Pinouts>
     <ns1:Properties>
      <ns1:SoapPropertyDescriptor>
       <ns1:Name></ns1:Name>
       <ns1:DataType></ns1:DataType>
       <ns1:Value></ns1:Value>
      </ns1:SoapPropertyDescriptor>
      <ns1:SoapPropertyDescriptor>
       <ns1:Name></ns1:Name>
       <ns1:DataType></ns1:DataType>
       <ns1:Value></ns1:Value>
      </ns1:SoapPropertyDescriptor>
     </ns1:Properties>
    </ns1:SoapDeviceDescriptor>
    <ns1:SoapDeviceDescriptor>
     <ns1:DeviceConnectionPoints>
      <ns1:SoapConnectionPointDescriptor>
       <ns1:Properties>
        <ns1:SoapPropertyDescriptor>
         <ns1:Name></ns1:Name>
         <ns1:DataType></ns1:DataType>
         <ns1:Value></ns1:Value>
        </ns1:SoapPropertyDescriptor>
        <ns1:SoapPropertyDescriptor>
         <ns1:Name></ns1:Name>
         <ns1:DataType></ns1:DataType>
         <ns1:Value></ns1:Value>
        </ns1:SoapPropertyDescriptor>
       </ns1:Properties>
      </ns1:SoapConnectionPointDescriptor>
      <ns1:SoapConnectionPointDescriptor>
       <ns1:Properties>
        <ns1:SoapPropertyDescriptor>
         <ns1:Name></ns1:Name>
         <ns1:DataType></ns1:DataType>
         <ns1:Value></ns1:Value>
        </ns1:SoapPropertyDescriptor>
        <ns1:SoapPropertyDescriptor>
         <ns1:Name></ns1:Name>
         <ns1:DataType></ns1:DataType>
         <ns1:Value></ns1:Value>
        </ns1:SoapPropertyDescriptor>
       </ns1:Properties>
      </ns1:SoapConnectionPointDescriptor>
     </ns1:DeviceConnectionPoints>
     <ns1:Pinouts>
      <ns1:SoapPinoutDescriptor>
       <ns1:SupportedCommands>
        <ns1:SoapCommandDescriptor>
         <ns1:CommandParameters>
         </ns1:CommandParameters>
         <ns1:Properties>
         </ns1:Properties>
        </ns1:SoapCommandDescriptor>
        <ns1:SoapCommandDescriptor>
         <ns1:CommandParameters>
         </ns1:CommandParameters>
         <ns1:Properties>
         </ns1:Properties>
        </ns1:SoapCommandDescriptor>
       </ns1:SupportedCommands>
       <ns1:SupportedEvents>
        <ns1:SoapEventDescriptor>
         <ns1:EventParameters>
         </ns1:EventParameters>
         <ns1:Properties>
         </ns1:Properties>
        </ns1:SoapEventDescriptor>
        <ns1:SoapEventDescriptor>
         <ns1:EventParameters>
         </ns1:EventParameters>
         <ns1:Properties>
         </ns1:Properties>
        </ns1:SoapEventDescriptor>
       </ns1:SupportedEvents>
       <ns1:Properties>
        <ns1:SoapPropertyDescriptor>
         <ns1:Name></ns1:Name>
         <ns1:DataType></ns1:DataType>
         <ns1:Value></ns1:Value>
        </ns1:SoapPropertyDescriptor>
        <ns1:SoapPropertyDescriptor>
         <ns1:Name></ns1:Name>
         <ns1:DataType></ns1:DataType>
         <ns1:Value></ns1:Value>
        </ns1:SoapPropertyDescriptor>
       </ns1:Properties>
      </ns1:SoapPinoutDescriptor>
      <ns1:SoapPinoutDescriptor>
       <ns1:SupportedCommands>
        <ns1:SoapCommandDescriptor>
         <ns1:CommandParameters>
         </ns1:CommandParameters>
         <ns1:Properties>
         </ns1:Properties>
        </ns1:SoapCommandDescriptor>
        <ns1:SoapCommandDescriptor>
         <ns1:CommandParameters>
         </ns1:CommandParameters>
         <ns1:Properties>
         </ns1:Properties>
        </ns1:SoapCommandDescriptor>
       </ns1:SupportedCommands>
       <ns1:SupportedEvents>
        <ns1:SoapEventDescriptor>
         <ns1:EventParameters>
         </ns1:EventParameters>
         <ns1:Properties>
         </ns1:Properties>
        </ns1:SoapEventDescriptor>
        <ns1:SoapEventDescriptor>
         <ns1:EventParameters>
         </ns1:EventParameters>
         <ns1:Properties>
         </ns1:Properties>
        </ns1:SoapEventDescriptor>
       </ns1:SupportedEvents>
       <ns1:Properties>
        <ns1:SoapPropertyDescriptor>
         <ns1:Name></ns1:Name>
         <ns1:DataType></ns1:DataType>
         <ns1:Value></ns1:Value>
        </ns1:SoapPropertyDescriptor>
        <ns1:SoapPropertyDescriptor>
         <ns1:Name></ns1:Name>
         <ns1:DataType></ns1:DataType>
         <ns1:Value></ns1:Value>
        </ns1:SoapPropertyDescriptor>
       </ns1:Properties>
      </ns1:SoapPinoutDescriptor>
     </ns1:Pinouts>
     <ns1:Properties>
      <ns1:SoapPropertyDescriptor>
       <ns1:Name></ns1:Name>
       <ns1:DataType></ns1:DataType>
       <ns1:Value></ns1:Value>
      </ns1:SoapPropertyDescriptor>
      <ns1:SoapPropertyDescriptor>
       <ns1:Name></ns1:Name>
       <ns1:DataType></ns1:DataType>
       <ns1:Value></ns1:Value>
      </ns1:SoapPropertyDescriptor>
     </ns1:Properties>
    </ns1:SoapDeviceDescriptor>
   </ns1:GetDevicesResult>
  </ns1:GetDevicesResponse>
 </SOAP-ENV:Body>
</SOAP-ENV:Envelope>
